md2lang_oai/__init__.py
md2lang_oai/__main__.py
md2lang_oai/chunker.py
md2lang_oai/cli.py
md2lang_oai/locale.py
md2lang_oai/oai.py
md2lang_oai/protect.py
md2lang_oai-1.1.0.dist-info/METADATA
md2lang_oai-1.1.0.dist-info/WHEEL
md2lang_oai-1.1.0.dist-info/entry_points.txt
md2lang_oai-1.1.0.dist-info/licenses/LICENSE
md2lang_oai-1.1.0.dist-info/RECORD
