Metadata-Version: 2.4
Name: md2lang-oai
Version: 1.1.0
Summary: Minimal CLI to translate Markdown/text to a target locale via an OpenAI-compatible Chat Completions endpoint.
Project-URL: Repository, https://github.com/carloscasalar/md2lang-oai
License: MIT License
License-File: LICENSE
Keywords: cli,markdown,openai,translation
Requires-Python: >=3.10
Requires-Dist: click>=8.1
Requires-Dist: httpx>=0.27
